encodingcom/__init__.py
encodingcom/encoding.py
encodingcom/encoding_utils.py
encodingcom/error_handler.py
encodingcom/exception.py
encodingcom/format.py
encodingcom/poller.py
encodingcom/request_template.py
encodingcom/response_helper.py
encodingcom/string_utils.py
encodingcom-0.1.3.data/data/README.md
encodingcom-0.1.3.dist-info/DESCRIPTION.rst
encodingcom-0.1.3.dist-info/METADATA
encodingcom-0.1.3.dist-info/metadata.json
encodingcom-0.1.3.dist-info/RECORD
encodingcom-0.1.3.dist-info/top_level.txt
encodingcom-0.1.3.dist-info/WHEEL
tools/__init__.py
tools/cancel_media.py
tools/job_status_monitor.py
tools/ls_queue.py
