Metadata-Version: 2.0
Name: encodingcom
Version: 0.1.3
Summary: Python 3 wrapper for Encoding.com api
Home-page: https://github.com/studionowinc/encodingcom
Author: Ryan Stubblefield, David Hwu
Author-email: pypi@studionow.com
License: UNKNOWN
Keywords: encoding.com transcoding
Platform: UNKNOWN
Classifier: Development Status :: 3 - Alpha
Classifier: Environment :: Web Environment
Classifier: Natural Language :: English
Classifier: Operating System :: POSIX
Classifier: Programming Language :: Python :: 3
Requires-Dist: requests (>=2.5.1)
